angrylibs/__init__.py
angrylibs/helpers.py
angrylibs/words.json
angrylibs/stories/bowling.story.txt
angrylibs/stories/driving_tips.story.txt
angrylibs/stories/going_for_a_hike.story.txt
angrylibs/stories/gopher_gulch.story.txt
angrylibs/stories/how_to_be_a_photographer.story.txt
angrylibs/stories/letter_from_camp.story.txt
angrylibs/stories/mr_snowman.story.txt
angrylibs/stories/one_more_game.story.txt
angrylibs/stories/school_nurse.story.txt
angrylibs-2.1.2.dist-info/LICENSE
angrylibs-2.1.2.dist-info/METADATA
angrylibs-2.1.2.dist-info/WHEEL
angrylibs-2.1.2.dist-info/entry_points.txt
angrylibs-2.1.2.dist-info/top_level.txt
angrylibs-2.1.2.dist-info/RECORD
