Metadata-Version: 2.1
Name: angrylibs
Version: 2.1.2
Summary: Have a fluffy time by making some slimy choices
Home-page: https://angry-libs.readthedocs.io
Author: Ben Soyka
Author-email: bensoyka@icloud.com
License: MIT
Project-URL: Documentation, https://angry-libs.readthedocs.io/
Project-URL: Changelog, https://github.com/bsoyka/angrylibs/blob/master/CHANGELOG.md
Platform: UNKNOWN
Classifier: Development Status :: 5 - Production/Stable
Classifier: Environment :: Console
Classifier: License :: OSI Approved :: MIT License
Classifier: Natural Language :: English
Classifier: Programming Language :: Python :: 3
Classifier: Programming Language :: Python :: 3 :: Only
Classifier: Programming Language :: Python :: 3.7
Classifier: Programming Language :: Python :: 3.8
Classifier: Programming Language :: Python :: 3.9
Classifier: Topic :: Games/Entertainment
Requires-Python: >=3.7
Requires-Dist: click (>=2.0)
Requires-Dist: inflect (>=4.0.0)
Requires-Dist: rich (>=5.0.0)
